README.rst
setup.cfg
setup.py
django_mongo_avatar.egg-info/PKG-INFO
django_mongo_avatar.egg-info/SOURCES.txt
django_mongo_avatar.egg-info/dependency_links.txt
django_mongo_avatar.egg-info/entry_points.txt
django_mongo_avatar.egg-info/requires.txt
django_mongo_avatar.egg-info/top_level.txt
mongo_avatar/__init__.py
mongo_avatar/admin.py
mongo_avatar/db.py
mongo_avatar/errors.py
mongo_avatar/helpers.py
mongo_avatar/models.py
mongo_avatar/query.py
mongo_avatar/tests.py
mongo_avatar/views.py
mongo_avatar/management/__init__.py
mongo_avatar/management/commands/__init__.py
mongo_avatar/management/commands/mongosync.py
mongo_avatar/migrations/__init__.py