Metadata-Version: 1.1
Name: django-mongo-avatar
Version: 1.0.0.dev8
Summary: A django like ORM for mongodb
Home-page: https://github.com/mharoonfsd/MongoAvatar
Author: Muhammad Haroon
Author-email: m.haroon.fsd@gmail.com
License: MIT
Keywords: mongodb orm django
Platform: UNKNOWN
Classifier: Development Status :: 3 - Alpha
Classifier: Intended Audience :: Developers
Classifier: Topic :: Software Development :: Build Tools
Classifier: License :: OSI Approved :: MIT License
Classifier: Programming Language :: Python :: 2
Classifier: Programming Language :: Python :: 2.6
Classifier: Programming Language :: Python :: 2.7
